LICENSE.txt
MANIFEST.in
README.txt
setup.py
doc/pycoon_deployment_descriptor.n3
doc/pycoon_bouml/128027.diagram
doc/pycoon_bouml/128076
doc/pycoon_bouml/128076.diagram
doc/pycoon_bouml/128204
doc/pycoon_bouml/128204.diagram
doc/pycoon_bouml/128332
doc/pycoon_bouml/128332.diagram
doc/pycoon_bouml/128460
doc/pycoon_bouml/128460.diagram
doc/pycoon_bouml/128588
doc/pycoon_bouml/128716
doc/pycoon_bouml/128716.diagram
doc/pycoon_bouml/128844
doc/pycoon_bouml/128972
doc/pycoon_bouml/128972.diagram
doc/pycoon_bouml/129100
doc/pycoon_bouml/129100.diagram
doc/pycoon_bouml/129228
doc/pycoon_bouml/129228.diagram
doc/pycoon_bouml/129356
doc/pycoon_bouml/129484
doc/pycoon_bouml/129612
doc/pycoon_bouml/129740
doc/pycoon_bouml/cpp_includes
doc/pycoon_bouml/generation_settings
doc/pycoon_bouml/idl_includes
doc/pycoon_bouml/java_imports
doc/pycoon_bouml/pycoon_bouml.prj
doc/pycoon_bouml/stereotypes
doc/pycoon_bouml/tools
legal/cherrypy.license.txt
legal/paste.license.txt
src/pycoon/__init__.py
src/pycoon/environment.py
src/pycoon/pycoon.xconf
src/pycoon/source.py
src/pycoon/variables.py
src/pycoon.egg-info/PKG-INFO
src/pycoon.egg-info/SOURCES.txt
src/pycoon.egg-info/dependency_links.txt
src/pycoon.egg-info/entry_points.txt
src/pycoon.egg-info/not-zip-safe
src/pycoon.egg-info/requires.txt
src/pycoon.egg-info/top_level.txt
src/pycoon/blocks/__init__.py
src/pycoon/blocks/fmt_textile/__init__.py
src/pycoon/blocks/fmt_textile/webapp/samples/hello-world.textile
src/pycoon/blocks/fmt_textile/webapp/samples/samples.xml
src/pycoon/blocks/fmt_textile/webapp/samples/sitemap.xmap
src/pycoon/blocks/fmt_textile/webapp/samples/somewhat-complicated.textile
src/pycoon/blocks/mgmt_statusgen/__init__.py
src/pycoon/blocks/mgmt_statusgen/webapp/samples/samples.xml
src/pycoon/blocks/mgmt_statusgen/webapp/samples/sitemap.xmap
src/pycoon/components/__init__.py
src/pycoon/components/cocoon.py
src/pycoon/components/tmp.py
src/pycoon/log/__init__.py
src/pycoon/sitemap/__init__.py
src/pycoon/sitemap/manager.py
src/pycoon/sitemap/nodes.py
src/pycoon/sitemap/treeprocessor.py
src/pycoon/webapp/sitemap.xmap
src/pycoon/webapp/welcome.html
src/pycoon/webapp/samples/samples.xml
