Metadata-Version: 1.0
Name: pycoon
Version: 0.2a5
Summary: Pythonic web development framework based on XML pipelines and WSGI
Home-page: http://code.google.com/p/pycoon/
Author: Andrey Nordin, Richard Lewis
Author-email: UNKNOWN
License: GNU GPL
Keywords: web framework xml pipeline wsgi middleware cocoon sitemap
Platform: UNKNOWN
